{
  "type": "bovinesandbuttercups:moobloom",
  "back_grass": {},
  "bud": {
    "model_location": "bovinesandbuttercups:bovinesandbuttercups/chargelily_bud"
  },
  "flower": {
    "block_state": {
      "Name": "bovinesandbuttercups:chargelily"
    }
  },
  "natural_spawns": [],
  "nectar_effects": [
    {
      "duration": 1200,
      "id": "minecraft:haste"
    }
  ],
  "nectar_palette": "bovinesandbuttercups:bovinesandbuttercups/item/chargelily_nectar_bowl",
  "particle": {
    "type": "bovinesandbuttercups:bloom",
    "color": 7584494
  }
}